[{"url":"https://www.yahoo.com","doms":3204},{"url":"https://www.sina.com.cn","doms":2989},{"url":"https://zoom.us","doms":2518},{"url":"https://www.shopify.com","doms":2265},{"url":"https://en.wikipedia.org/wiki/Main_Page","doms":2254},{"url":"https://www.360.cn","doms":1536},{"url":"https://www.wikipedia.org","doms":1176},{"url":"https://www.microsoft.com","doms":948},{"url":"https://www.office.com","doms":941},{"url":"https://www.netflix.com","doms":928},{"url":"https://www.sohu.com","doms":772},{"url":"https://www.okezone.com","doms":731},{"url":"https://www.jd.com/?country=USA","doms":559},{"url":"https://www.qq.com","doms":502},{"url":"https://www.baidu.com","doms":461},{"url":"https://www.youtube.com","doms":416},{"url":"https://www.tmall.com","doms":392},{"url":"https://taobao.com","doms":276},{"url":"https://www.instagram.com","doms":208},{"url":"https://www.facebook.com","doms":183},{"url":"https://vk.com","doms":120},{"url":"https://www.google.com/search?q=justjavac","doms":95},{"url":"https://live.com","doms":86},{"url":"https://www.google.com","doms":80},{"url":"https://www.amazon.com","doms":48},{"url":"https://www.alipay.com","doms":40},{"url":"https://www.baidu.com/s?ie=UTF-8&wd=justjavac","doms":23},{"url":"https://weibo.com","doms":9},{"url":"https://www.reddit.com","doms":-1,"error":"Forbidden"},{"url":"http://xinhuanet.com","doms":-1,"error":"Service Unavailable"},{"url":"https://www.csdn.net","doms":-1,"error":""},{"url":"https://panda.tv","doms":-1,"error":"Forbidden"},{"url":"http://microsoftonline.com","doms":-1,"error":"error sending request for url (http://microsoftonline.com/): client error (Connect): dns error: failed to lookup address information: No address associated with hostname: failed to lookup address information: No address associated with hostname"}]